geocraft/__init__.py
geocraft/_scripts/__init__.py
geocraft/_scripts/coord_convert.py
geocraft/_scripts/parse_baidumap.py
geocraft/coord_converter/__init__.py
geocraft/coord_converter/_classes.py
geocraft/coord_converter/_converter.py
geocraft/unstable/__init__.py
geocraft/unstable/_baidumap_parser.py
geocraft/unstable/_classes.py
geocraft-0.3.4.dist-info/METADATA
geocraft-0.3.4.dist-info/WHEEL
geocraft-0.3.4.dist-info/entry_points.txt
geocraft-0.3.4.dist-info/RECORD
