Metadata-Version: 2.1
Name: geocraft
Version: 0.3.4
Summary: Python library for Geo & WebGIS.
Author: Shangjin Tang
Author-email: shangjin.tang@gmail.com
Requires-Python: >=3.9,<4.0
Classifier: Programming Language :: Python :: 3
Classifier: Programming Language :: Python :: 3.9
Classifier: Programming Language :: Python :: 3.10
Classifier: Programming Language :: Python :: 3.11
Classifier: Programming Language :: Python :: 3.12
Requires-Dist: requests (>=2.32.3,<3.0.0)
